pyneurons/__init__.py
pyneurons/abs.py
pyneurons/apply.py
pyneurons/bias.py
pyneurons/binary.py
pyneurons/bind.py
pyneurons/box.py
pyneurons/compose.py
pyneurons/concat.py
pyneurons/create.py
pyneurons/explode.py
pyneurons/fit.py
pyneurons/gd.py
pyneurons/identity.py
pyneurons/implode.py
pyneurons/loss.py
pyneurons/mae.py
pyneurons/model.py
pyneurons/mse.py
pyneurons/param.py
pyneurons/phi.py
pyneurons/relu.py
pyneurons/relu1.py
pyneurons/relun.py
pyneurons/split.py
pyneurons/stack.py
pyneurons/unstack.py
pyneurons/vector.py
pyneurons/vjp/__init__.py
pyneurons/vjp/identity.py
pyneurons/vjp/sign.py
pyneurons/weight.py
pyneurons-0.3.5.dist-info/LICENSE
pyneurons-0.3.5.dist-info/METADATA
pyneurons-0.3.5.dist-info/WHEEL
pyneurons-0.3.5.dist-info/RECORD
