Metadata-Version: 2.1
Name: pyneurons
Version: 0.3.5
Summary: Composable neurons in JAX
Home-page: https://github.com/ivandustin/pyneurons
License: MIT
Author: Ivan Dustin Bilon
Author-email: ivan22.dust@gmail.com
Requires-Python: >=3.9,<4.0
Classifier: License :: OSI Approved :: MIT License
Classifier: Programming Language :: Python :: 3
Classifier: Programming Language :: Python :: 3.9
Classifier: Programming Language :: Python :: 3.10
Classifier: Programming Language :: Python :: 3.11
Classifier: Programming Language :: Python :: 3.12
Requires-Dist: jax (>=0.4.28,<0.5.0)
Requires-Dist: jaxlib (>=0.4.28,<0.5.0)
Requires-Dist: multipledispatch (>=0.6.0,<0.7.0)
Project-URL: Repository, https://github.com/ivandustin/pyneurons
